{"_path":"/articles/start-again","_dir":"articles","_draft":false,"_partial":false,"_locale":"","title":"Start Again","description":"","cover":"/skull with flowers","date":"2024-01-31T00:00:00.000Z","body":{"type":"root","children":[{"type":"element","tag":"nuxt-img","props":{"alt":"skull with flowers","src":"/skull%20with%20flowers"},"children":[]}],"toc":{"title":"","searchDepth":2,"depth":2,"links":[]}},"_type":"markdown","_id":"content:articles:Start Again.md","_source":"content","_file":"articles/Start Again.md","_stem":"articles/Start Again","_extension":"md"}